sparksampling/__init__.py
sparksampling/app.py
sparksampling/config.py
sparksampling/default_app_config.py
sparksampling/engine_factory.py
sparksampling/error.py
sparksampling/mixin.py
sparksampling/sdk.py
sparksampling/service.py
sparksampling/utilities.py
sparksampling/engine/__init__.py
sparksampling/engine/base_engine.py
sparksampling/engine/dummy_engine.py
sparksampling/engine/rms_engine.py
sparksampling/engine/sms_engine.py
sparksampling/engine/stop_engine.py
sparksampling/evaluation/__init__.py
sparksampling/evaluation/base_hook.py
sparksampling/evaluation/dummy_hook.py
sparksampling/evaluation/hook_msg.py
sparksampling/evaluation/warn_hook.py
sparksampling/evaluation_extension/__init__.py
sparksampling/evaluation_extension/dummy_extension/__init__.py
sparksampling/evaluation_extension/dummy_extension/dummy_hook.py
sparksampling/file_format/__init__.py
sparksampling/file_format/base_file_format.py
sparksampling/file_format/csv_file_imp.py
sparksampling/file_format/file_factory.py
sparksampling/file_format/output_adapter.py
sparksampling/proto/__init__.py
sparksampling/proto/sampling_service_pb2.py
sparksampling/proto/sampling_service_pb2_grpc.py
sparksampling/sample/__init__.py
sparksampling/sample/base_sampling.py
sparksampling/sample/cluster_sampling_imp.py
sparksampling/sample/random_sampling_imp.py
sparksampling/sample/sampling_factory.py
sparksampling/sample/simple_sampling_imp.py
sparksampling/sample/stratified_sampling_imp.py
sparksampling-0.4.2.dist-info/METADATA
sparksampling-0.4.2.dist-info/WHEEL
sparksampling-0.4.2.dist-info/entry_points.txt
sparksampling-0.4.2.dist-info/licenses/LICENSE
sparksampling-0.4.2.dist-info/RECORD
