Metadata-Version: 2.1
Name: sparksampling
Version: 0.4.2
Summary: pyspark-sampling
Project-URL: Source, https://github.com/Wh1isper/pyspark-sampling
Author-email: Wh1isper <9573586@qq.com>
License: Apache License 2.0
License-File: LICENSE
Keywords: pyspark-sampling,sparksampling
Classifier: Development Status :: 2 - Pre-Alpha
Classifier: Intended Audience :: Developers
Classifier: Natural Language :: English
Classifier: Programming Language :: Python :: 3
Classifier: Programming Language :: Python :: 3.7
Classifier: Programming Language :: Python :: 3.8
Classifier: Programming Language :: Python :: 3.9
Classifier: Programming Language :: Python :: 3.10
Requires-Python: >=3.7
Requires-Dist: boto3
Requires-Dist: findspark
Requires-Dist: graphlib-backport; python_version <= '3.8'
Requires-Dist: grpcio-tools
Requires-Dist: kubernetes
Requires-Dist: pandas>=1.2
Requires-Dist: pyspark
Requires-Dist: requests
Requires-Dist: sparglim
Requires-Dist: sparksampling-proto>=0.1.0
Requires-Dist: traitlets
Provides-Extra: test
Requires-Dist: pre-commit; extra == 'test'
Requires-Dist: pytest; extra == 'test'
Requires-Dist: pytest-grpc; extra == 'test'
